{"name":"InteractionResult$SwingSource","package":"net.minecraft.world","fqn":"net.minecraft.world.InteractionResult$SwingSource","type":"class","members":["public static final net.minecraft.world.InteractionResult$SwingSource NONE;","public static final net.minecraft.world.InteractionResult$SwingSource CLIENT;","public static final net.minecraft.world.InteractionResult$SwingSource SERVER;","private static final net.minecraft.world.InteractionResult$SwingSource[] $VALUES;","public static net.minecraft.world.InteractionResult$SwingSource[] values();","public static net.minecraft.world.InteractionResult$SwingSource valueOf(java.lang.String);","private net.minecraft.world.InteractionResult$SwingSource();","private static net.minecraft.world.InteractionResult$SwingSource[] $values();","static {};"],"references":[],"usages":[]}
