{"name":"VertexFormat$Builder","package":"com.mojang.blaze3d.vertex","fqn":"com.mojang.blaze3d.vertex.VertexFormat$Builder","type":"class","members":["private final com.google.common.collect.ImmutableMap$Builder<java.lang.String, com.mojang.blaze3d.vertex.VertexFormatElement> elements;","private final it.unimi.dsi.fastutil.ints.IntList offsets;","private int offset;","private com.mojang.blaze3d.vertex.VertexFormat$Builder();","public com.mojang.blaze3d.vertex.VertexFormat$Builder add(java.lang.String, com.mojang.blaze3d.vertex.VertexFormatElement);","public com.mojang.blaze3d.vertex.VertexFormat$Builder padding(int);","public com.mojang.blaze3d.vertex.VertexFormat build();"],"references":["com.google.common.collect.ImmutableMap.builder","it.unimi.dsi.fastutil.ints.IntArrayList","com.google.common.collect.ImmutableMap$Builder.put","it.unimi.dsi.fastutil.ints.IntList.add","com.mojang.blaze3d.vertex.VertexFormatElement.byteSize","com.google.common.collect.ImmutableMap$Builder.buildOrThrow","com.google.common.collect.ImmutableMap.values","com.google.common.collect.ImmutableCollection.asList","com.google.common.collect.ImmutableMap.keySet","com.google.common.collect.ImmutableSet.asList","com.mojang.blaze3d.vertex.VertexFormat"],"usages":["com.mojang.blaze3d.vertex.VertexFormat"]}
