{"name":"SpawnContext","package":"net.minecraft.world.entity.variant","fqn":"net.minecraft.world.entity.variant.SpawnContext","type":"class","members":["private final net.minecraft.core.BlockPos pos;","private final net.minecraft.world.level.ServerLevelAccessor level;","private final net.minecraft.world.attribute.EnvironmentAttributeReader environmentAttributes;","private final net.minecraft.core.Holder<net.minecraft.world.level.biome.Biome> biome;","public net.minecraft.world.entity.variant.SpawnContext(net.minecraft.core.BlockPos, net.minecraft.world.level.ServerLevelAccessor, net.minecraft.world.attribute.EnvironmentAttributeReader, net.minecraft.core.Holder<net.minecraft.world.level.biome.Biome>);","public static net.minecraft.world.entity.variant.SpawnContext create(net.minecraft.world.level.ServerLevelAccessor, net.minecraft.core.BlockPos);","public final java.lang.String toString();","public final int hashCode();","public final boolean equals(java.lang.Object);","public net.minecraft.core.BlockPos pos();","public net.minecraft.world.level.ServerLevelAccessor level();","public net.minecraft.world.attribute.EnvironmentAttributeReader environmentAttributes();","public net.minecraft.core.Holder<net.minecraft.world.level.biome.Biome> biome();"],"references":["net.minecraft.world.level.ServerLevelAccessor.getBiome","net.minecraft.world.level.ServerLevelAccessor.environmentAttributes"],"usages":["net.minecraft.world.entity.variant.BiomeCheck","net.minecraft.world.entity.variant.MoonBrightnessCheck","net.minecraft.world.entity.variant.StructureCheck"]}
