{"name":"FlyingMoveControl","package":"net.minecraft.world.entity.ai.control","fqn":"net.minecraft.world.entity.ai.control.FlyingMoveControl","type":"class","members":["private final int maxTurn;","private final boolean hoversInPlace;","public net.minecraft.world.entity.ai.control.FlyingMoveControl(net.minecraft.world.entity.Mob, int, boolean);","public void tick();"],"references":["net.minecraft.world.entity.ai.control.MoveControl","net.minecraft.world.entity.ai.control.MoveControl$Operation.MOVE_TO","net.minecraft.world.entity.ai.control.MoveControl$Operation.WAIT","net.minecraft.world.entity.Mob.setNoGravity","net.minecraft.world.entity.Mob.getX","net.minecraft.world.entity.Mob.getY","net.minecraft.world.entity.Mob.getZ","net.minecraft.world.entity.Mob.setYya","net.minecraft.world.entity.Mob.setZza","net.minecraft.util.Mth.atan2","net.minecraft.world.entity.Mob.getYRot","net.minecraft.world.entity.Mob.setYRot","net.minecraft.world.entity.Mob.onGround","net.minecraft.world.entity.ai.attributes.Attributes.MOVEMENT_SPEED","net.minecraft.world.entity.Mob.getAttributeValue","net.minecraft.world.entity.ai.attributes.Attributes.FLYING_SPEED","net.minecraft.world.entity.Mob.setSpeed","net.minecraft.world.entity.Mob.getXRot","net.minecraft.world.entity.Mob.setXRot"],"usages":["net.minecraft.world.entity.animal.allay.Allay","net.minecraft.world.entity.animal.bee.Bee","net.minecraft.world.entity.animal.happyghast.HappyGhast","net.minecraft.world.entity.animal.parrot.Parrot","net.minecraft.world.entity.boss.wither.WitherBoss"]}
