{"name":"GameRenderer$1","package":"net.minecraft.client.renderer","fqn":"net.minecraft.client.renderer.GameRenderer$1","type":"class","members":["private int index;","final net.minecraft.client.gui.render.state.GuiTextRenderState val$text;","final net.minecraft.client.renderer.GameRenderer this$0;","net.minecraft.client.renderer.GameRenderer$1();","public void acceptGlyph(net.minecraft.client.gui.font.TextRenderable$Styled);","public void acceptEmptyArea(net.minecraft.client.gui.font.EmptyArea);","private void renderDebugMarkers(net.minecraft.client.gui.font.ActiveArea, boolean);"],"references":["net.minecraft.client.gui.font.ActiveArea.style","net.minecraft.network.chat.Style.getClickEvent","net.minecraft.network.chat.Style.getHoverEvent","net.minecraft.util.ARGB.color","net.minecraft.client.renderer.GameRenderer.guiRenderState","net.minecraft.client.gui.render.state.ColoredRectangleRenderState","net.minecraft.client.renderer.RenderPipelines.GUI","net.minecraft.client.gui.render.TextureSetup.noTexture","net.minecraft.client.gui.render.state.GuiTextRenderState.pose","net.minecraft.client.gui.font.ActiveArea.activeLeft","net.minecraft.client.gui.font.ActiveArea.activeTop","net.minecraft.client.gui.font.ActiveArea.activeRight","net.minecraft.client.gui.font.ActiveArea.activeBottom","net.minecraft.client.gui.render.state.GuiTextRenderState.scissor","net.minecraft.client.gui.render.state.GuiRenderState.submitGuiElement"],"usages":["net.minecraft.client.renderer.GameRenderer"]}
