{"name":"ItemInHandRenderer$1","package":"net.minecraft.client.renderer","fqn":"net.minecraft.client.renderer.ItemInHandRenderer$1","type":"class","members":["static final int[] $SwitchMap$net$minecraft$world$item$ItemUseAnimation;","static final int[] $SwitchMap$net$minecraft$world$item$SwingAnimationType;","static {};"],"references":["net.minecraft.world.item.SwingAnimationType.values","net.minecraft.world.item.SwingAnimationType.NONE","net.minecraft.world.item.SwingAnimationType.ordinal","net.minecraft.world.item.SwingAnimationType.WHACK","net.minecraft.world.item.SwingAnimationType.STAB","net.minecraft.world.item.ItemUseAnimation.values","net.minecraft.world.item.ItemUseAnimation.NONE","net.minecraft.world.item.ItemUseAnimation.ordinal","net.minecraft.world.item.ItemUseAnimation.EAT","net.minecraft.world.item.ItemUseAnimation.DRINK","net.minecraft.world.item.ItemUseAnimation.BLOCK","net.minecraft.world.item.ItemUseAnimation.BOW","net.minecraft.world.item.ItemUseAnimation.TRIDENT","net.minecraft.world.item.ItemUseAnimation.BRUSH","net.minecraft.world.item.ItemUseAnimation.BUNDLE","net.minecraft.world.item.ItemUseAnimation.SPEAR"],"usages":[]}
