{"name":"LoggedChatEvent$Type","package":"net.minecraft.client.multiplayer.chat","fqn":"net.minecraft.client.multiplayer.chat.LoggedChatEvent$Type","type":"class","members":["public static final net.minecraft.client.multiplayer.chat.LoggedChatEvent$Type PLAYER;","public static final net.minecraft.client.multiplayer.chat.LoggedChatEvent$Type SYSTEM;","private final java.lang.String serializedName;","private final java.util.function.Supplier<com.mojang.serialization.MapCodec<? extends net.minecraft.client.multiplayer.chat.LoggedChatEvent>> codec;","private static final net.minecraft.client.multiplayer.chat.LoggedChatEvent$Type[] $VALUES;","public static net.minecraft.client.multiplayer.chat.LoggedChatEvent$Type[] values();","public static net.minecraft.client.multiplayer.chat.LoggedChatEvent$Type valueOf(java.lang.String);","private net.minecraft.client.multiplayer.chat.LoggedChatEvent$Type(java.lang.String, java.util.function.Supplier<com.mojang.serialization.MapCodec<? extends net.minecraft.client.multiplayer.chat.LoggedChatEvent>>);","private com.mojang.serialization.MapCodec<? extends net.minecraft.client.multiplayer.chat.LoggedChatEvent> codec();","public java.lang.String getSerializedName();","private static com.mojang.serialization.MapCodec lambda$static$1();","private static com.mojang.serialization.MapCodec lambda$static$0();","private static net.minecraft.client.multiplayer.chat.LoggedChatEvent$Type[] $values();","static {};"],"references":["com.mojang.serialization.MapCodec","net.minecraft.client.multiplayer.chat.LoggedChatMessage$System.CODEC","net.minecraft.client.multiplayer.chat.LoggedChatMessage$Player.CODEC"],"usages":[]}
