{"name":"FurnaceMenu","package":"net.minecraft.world.inventory","fqn":"net.minecraft.world.inventory.FurnaceMenu","type":"class","members":["public net.minecraft.world.inventory.FurnaceMenu(int, net.minecraft.world.entity.player.Inventory);","public net.minecraft.world.inventory.FurnaceMenu(int, net.minecraft.world.entity.player.Inventory, net.minecraft.world.Container, net.minecraft.world.inventory.ContainerData);"],"references":["net.minecraft.world.inventory.MenuType.FURNACE","net.minecraft.world.item.crafting.RecipeType.SMELTING","net.minecraft.world.item.crafting.RecipePropertySet.FURNACE_INPUT","net.minecraft.world.inventory.RecipeBookType.FURNACE","net.minecraft.world.inventory.AbstractFurnaceMenu"],"usages":["net.minecraft.world.level.block.entity.FurnaceBlockEntity"]}
