{"name":"RecipeBookMenu","package":"net.minecraft.world.inventory","fqn":"net.minecraft.world.inventory.RecipeBookMenu","type":"class","members":["public net.minecraft.world.inventory.RecipeBookMenu(net.minecraft.world.inventory.MenuType<?>, int);","public abstract net.minecraft.world.inventory.RecipeBookMenu$PostPlaceAction handlePlacement(boolean, boolean, net.minecraft.world.item.crafting.RecipeHolder<?>, net.minecraft.server.level.ServerLevel, net.minecraft.world.entity.player.Inventory);","public abstract void fillCraftSlotsStackedContents(net.minecraft.world.entity.player.StackedItemContents);","public abstract net.minecraft.world.inventory.RecipeBookType getRecipeBookType();"],"references":["net.minecraft.world.inventory.AbstractContainerMenu"],"usages":["net.minecraft.server.network.ServerGamePacketListenerImpl","net.minecraft.world.inventory.AbstractCraftingMenu","net.minecraft.world.inventory.AbstractFurnaceMenu"]}
