{"name":"ArrowGizmo","package":"net.minecraft.gizmos","fqn":"net.minecraft.gizmos.ArrowGizmo","type":"class","members":["private final net.minecraft.world.phys.Vec3 start;","private final net.minecraft.world.phys.Vec3 end;","private final int color;","private final float width;","public static final float DEFAULT_WIDTH;","public net.minecraft.gizmos.ArrowGizmo(net.minecraft.world.phys.Vec3, net.minecraft.world.phys.Vec3, int, float);","public void emit(net.minecraft.gizmos.GizmoPrimitives, float);","public final java.lang.String toString();","public final int hashCode();","public final boolean equals(java.lang.Object);","public net.minecraft.world.phys.Vec3 start();","public net.minecraft.world.phys.Vec3 end();","public int color();","public float width();"],"references":["net.minecraft.util.ARGB.multiplyAlpha","net.minecraft.gizmos.GizmoPrimitives.addLine","org.joml.Quaternionf","org.joml.Vector3f","net.minecraft.world.phys.Vec3.subtract","net.minecraft.world.phys.Vec3.toVector3f","org.joml.Vector3f.normalize","org.joml.Quaternionf.rotationTo","net.minecraft.world.phys.Vec3.distanceTo","net.minecraft.util.Mth.clamp","org.joml.Quaternionf.transform","org.joml.Vector3f.x","org.joml.Vector3f.y","org.joml.Vector3f.z","net.minecraft.world.phys.Vec3.add"],"usages":["net.minecraft.gizmos.Gizmos"]}
