{"name":"RealmsWorldUploadStatusTracker","package":"com.mojang.realmsclient.client.worldupload","fqn":"com.mojang.realmsclient.client.worldupload.RealmsWorldUploadStatusTracker","type":"interface","members":["public abstract com.mojang.realmsclient.client.UploadStatus getUploadStatus();","public abstract void setUploading();","public static com.mojang.realmsclient.client.worldupload.RealmsWorldUploadStatusTracker noOp();"],"references":["com.mojang.realmsclient.client.worldupload.RealmsWorldUploadStatusTracker$1"],"usages":[]}
