{"name":"EncoderCache","package":"net.minecraft.util","fqn":"net.minecraft.util.EncoderCache","type":"class","members":["private final com.google.common.cache.LoadingCache<net.minecraft.util.EncoderCache$Key<?, ?>, com.mojang.serialization.DataResult<?>> cache;","public net.minecraft.util.EncoderCache(int);","public <A> com.mojang.serialization.Codec<A> wrap(com.mojang.serialization.Codec<A>);"],"references":["com.google.common.cache.CacheBuilder.newBuilder","com.google.common.cache.CacheBuilder.maximumSize","com.google.common.cache.CacheBuilder.concurrencyLevel","com.google.common.cache.CacheBuilder.softValues","net.minecraft.util.EncoderCache$1","com.google.common.cache.CacheBuilder.build","net.minecraft.util.EncoderCache$2"],"usages":["net.minecraft.core.component.DataComponents"]}
