{"name":"FileUtil","package":"net.minecraft.util","fqn":"net.minecraft.util.FileUtil","type":"class","members":["private static final java.util.regex.Pattern COPY_COUNTER_PATTERN;","private static final int MAX_FILE_NAME;","private static final java.util.regex.Pattern RESERVED_WINDOWS_FILENAMES;","private static final java.util.regex.Pattern STRICT_PATH_SEGMENT_CHECK;","public net.minecraft.util.FileUtil();","public static java.lang.String sanitizeName(java.lang.String);","public static java.lang.String findAvailableName(java.nio.file.Path, java.lang.String, java.lang.String) throws java.io.IOException;","public static boolean isPathNormalized(java.nio.file.Path);","public static boolean isPathPortable(java.nio.file.Path);","public static boolean isPathPartPortable(java.lang.String);","public static java.nio.file.Path createPathToResource(java.nio.file.Path, java.lang.String, java.lang.String);","public static java.lang.String getFullResourcePath(java.lang.String);","public static java.lang.String normalizeResourcePath(java.lang.String);","public static com.mojang.serialization.DataResult<java.util.List<java.lang.String>> decomposePath(java.lang.String);","public static java.nio.file.Path resolvePath(java.nio.file.Path, java.util.List<java.lang.String>);","private static boolean containsAllowedCharactersOnly(java.lang.String);","public static boolean isValidPathSegment(java.lang.String);","public static void validatePath(java.lang.String...);","public static void createDirectoriesSafe(java.nio.file.Path) throws java.io.IOException;","private static java.lang.String lambda$decomposePath$3(java.lang.String, java.lang.String);","private static java.lang.String lambda$decomposePath$2(java.lang.String, java.lang.String);","private static java.lang.String lambda$decomposePath$1(java.lang.String);","private static java.lang.String lambda$decomposePath$0(java.lang.String);","static {};"],"references":["net.minecraft.SharedConstants.ILLEGAL_FILE_CHARACTERS","org.apache.commons.io.FilenameUtils.getFullPath","org.apache.commons.io.FilenameUtils.normalize","com.mojang.serialization.DataResult.error","com.mojang.serialization.DataResult.success"],"usages":[]}
