{"name":"SortedArraySet","package":"net.minecraft.util","fqn":"net.minecraft.util.SortedArraySet","type":"class","members":["private static final int DEFAULT_INITIAL_CAPACITY;","private final java.util.Comparator<T> comparator;","private T[] contents;","private int size;","private net.minecraft.util.SortedArraySet(int, java.util.Comparator<T>);","public static <T extends java.lang.Comparable<T>> net.minecraft.util.SortedArraySet<T> create();","public static <T extends java.lang.Comparable<T>> net.minecraft.util.SortedArraySet<T> create(int);","public static <T> net.minecraft.util.SortedArraySet<T> create(java.util.Comparator<T>);","public static <T> net.minecraft.util.SortedArraySet<T> create(java.util.Comparator<T>, int);","private static <T> T[] castRawArray(java.lang.Object[]);","private int findIndex(T);","private static int getInsertionPosition(int);","public boolean add(T);","private void grow(int);","private void addInternal(T, int);","private void removeInternal(int);","private T getInternal(int);","public T addOrGet(T);","public boolean remove(java.lang.Object);","public T get(T);","public T first();","public T last();","public boolean contains(java.lang.Object);","public java.util.Iterator<T> iterator();","public int size();","public java.lang.Object[] toArray();","public <U> U[] toArray(U[]);","public void clear();","public boolean equals(java.lang.Object);"],"references":["it.unimi.dsi.fastutil.objects.ObjectArrays.DEFAULT_EMPTY_ARRAY","net.minecraft.util.Util.growByHalf","net.minecraft.util.SortedArraySet$ArrayIterator"],"usages":[]}
