{"name":"HoglinRenderState","package":"net.minecraft.client.renderer.entity.state","fqn":"net.minecraft.client.renderer.entity.state.HoglinRenderState","type":"class","members":["public int attackAnimationRemainingTicks;","public boolean isConverting;","public net.minecraft.client.renderer.entity.state.HoglinRenderState();"],"references":["net.minecraft.client.renderer.entity.state.LivingEntityRenderState"],"usages":["net.minecraft.client.model.monster.hoglin.HoglinModel","net.minecraft.client.renderer.entity.AbstractHoglinRenderer","net.minecraft.client.renderer.entity.HoglinRenderer","net.minecraft.client.renderer.entity.ZoglinRenderer"]}
