{"name":"ChestRenderState","package":"net.minecraft.client.renderer.blockentity.state","fqn":"net.minecraft.client.renderer.blockentity.state.ChestRenderState","type":"class","members":["public net.minecraft.world.level.block.state.properties.ChestType type;","public float open;","public float angle;","public net.minecraft.client.renderer.blockentity.state.ChestRenderState$ChestMaterialType material;","public net.minecraft.client.renderer.blockentity.state.ChestRenderState();"],"references":["net.minecraft.client.renderer.blockentity.state.BlockEntityRenderState","net.minecraft.world.level.block.state.properties.ChestType.SINGLE","net.minecraft.client.renderer.blockentity.state.ChestRenderState$ChestMaterialType.REGULAR"],"usages":["net.minecraft.client.renderer.blockentity.ChestRenderer"]}
