{"name":"ServerboundPickItemFromBlockPacket","package":"net.minecraft.network.protocol.game","fqn":"net.minecraft.network.protocol.game.ServerboundPickItemFromBlockPacket","type":"class","members":["private final net.minecraft.core.BlockPos pos;","private final boolean includeData;","public static final net.minecraft.network.codec.StreamCodec<io.netty.buffer.ByteBuf, net.minecraft.network.protocol.game.ServerboundPickItemFromBlockPacket> STREAM_CODEC;","public net.minecraft.network.protocol.game.ServerboundPickItemFromBlockPacket(net.minecraft.core.BlockPos, boolean);","public net.minecraft.network.protocol.PacketType<net.minecraft.network.protocol.game.ServerboundPickItemFromBlockPacket> type();","public void handle(net.minecraft.network.protocol.game.ServerGamePacketListener);","public final java.lang.String toString();","public final int hashCode();","public final boolean equals(java.lang.Object);","public net.minecraft.core.BlockPos pos();","public boolean includeData();","public void handle(net.minecraft.network.PacketListener);","static {};"],"references":["net.minecraft.network.protocol.game.GamePacketTypes.SERVERBOUND_PICK_ITEM_FROM_BLOCK","net.minecraft.network.protocol.game.ServerGamePacketListener.handlePickItemFromBlock","net.minecraft.network.protocol.game.ServerGamePacketListener","net.minecraft.core.BlockPos.STREAM_CODEC","net.minecraft.network.codec.ByteBufCodecs.BOOL","net.minecraft.network.codec.StreamCodec.composite"],"usages":["net.minecraft.client.multiplayer.MultiPlayerGameMode"]}
