{"name":"Stitcher$Region","package":"net.minecraft.client.renderer.texture","fqn":"net.minecraft.client.renderer.texture.Stitcher$Region","type":"class","members":["private final int originX;","private final int originY;","private final int width;","private final int height;","private java.util.List<net.minecraft.client.renderer.texture.Stitcher$Region<T>> subSlots;","private net.minecraft.client.renderer.texture.Stitcher$Holder<T> holder;","public net.minecraft.client.renderer.texture.Stitcher$Region(int, int, int, int);","public int getX();","public int getY();","public boolean add(net.minecraft.client.renderer.texture.Stitcher$Holder<T>);","public void walk(net.minecraft.client.renderer.texture.Stitcher$SpriteLoader<T>, int);","public java.lang.String toString();"],"references":["net.minecraft.client.renderer.texture.Stitcher$Holder.width","net.minecraft.client.renderer.texture.Stitcher$Holder.height","net.minecraft.client.renderer.texture.Stitcher$Holder.entry","net.minecraft.client.renderer.texture.Stitcher$SpriteLoader.load"],"usages":["net.minecraft.client.renderer.texture.Stitcher"]}
