{"name":"ItemPickupParticleGroup","package":"net.minecraft.client.particle","fqn":"net.minecraft.client.particle.ItemPickupParticleGroup","type":"class","members":["public net.minecraft.client.particle.ItemPickupParticleGroup(net.minecraft.client.particle.ParticleEngine);","public net.minecraft.client.renderer.state.ParticleGroupRenderState extractRenderState(net.minecraft.client.renderer.culling.Frustum, net.minecraft.client.Camera, float);","private static net.minecraft.client.particle.ItemPickupParticleGroup$ParticleInstance lambda$extractRenderState$0(net.minecraft.client.Camera, float, net.minecraft.client.particle.ItemPickupParticle);"],"references":["net.minecraft.client.particle.ParticleGroup","net.minecraft.client.particle.ItemPickupParticleGroup$State","net.minecraft.client.particle.ItemPickupParticleGroup$ParticleInstance.fromParticle"],"usages":["net.minecraft.client.particle.ParticleEngine"]}
