{"name":"VanillaTheEndAdvancements","package":"net.minecraft.data.advancements.packs","fqn":"net.minecraft.data.advancements.packs.VanillaTheEndAdvancements","type":"class","members":["public net.minecraft.data.advancements.packs.VanillaTheEndAdvancements();","public void generate(net.minecraft.core.HolderLookup$Provider, java.util.function.Consumer<net.minecraft.advancements.AdvancementHolder>);"],"references":["net.minecraft.core.registries.Registries.ENTITY_TYPE","net.minecraft.core.HolderLookup$Provider.lookupOrThrow","net.minecraft.advancements.Advancement$Builder.advancement","net.minecraft.world.level.block.Blocks.END_STONE","net.minecraft.network.chat.Component.translatable","net.minecraft.resources.Identifier.withDefaultNamespace","net.minecraft.advancements.AdvancementType.TASK","net.minecraft.advancements.Advancement$Builder.display","net.minecraft.world.level.Level.END","net.minecraft.advancements.criterion.ChangeDimensionTrigger$TriggerInstance.changedDimensionTo","net.minecraft.advancements.Advancement$Builder.addCriterion","net.minecraft.advancements.Advancement$Builder.save","net.minecraft.advancements.Advancement$Builder.parent","net.minecraft.world.level.block.Blocks.DRAGON_HEAD","net.minecraft.advancements.criterion.EntityPredicate$Builder.entity","net.minecraft.world.entity.EntityType.ENDER_DRAGON","net.minecraft.advancements.criterion.EntityPredicate$Builder.of","net.minecraft.advancements.criterion.KilledTrigger$TriggerInstance.playerKilledEntity","net.minecraft.world.item.Items.ENDER_PEARL","net.minecraft.world.level.block.Blocks.END_GATEWAY","net.minecraft.advancements.criterion.EnterBlockTrigger$TriggerInstance.entersBlock","net.minecraft.world.item.Items.END_CRYSTAL","net.minecraft.advancements.AdvancementType.GOAL","net.minecraft.advancements.criterion.SummonedEntityTrigger$TriggerInstance.summonedEntity","net.minecraft.world.level.block.Blocks.PURPUR_BLOCK","net.minecraft.core.registries.Registries.STRUCTURE","net.minecraft.world.level.levelgen.structure.BuiltinStructures.END_CITY","net.minecraft.core.HolderLookup$RegistryLookup.getOrThrow","net.minecraft.advancements.criterion.LocationPredicate$Builder.inStructure","net.minecraft.advancements.criterion.PlayerTrigger$TriggerInstance.located","net.minecraft.world.item.Items.DRAGON_BREATH","net.minecraft.world.level.ItemLike","net.minecraft.advancements.criterion.InventoryChangeTrigger$TriggerInstance.hasItems","net.minecraft.world.item.Items.SHULKER_SHELL","net.minecraft.advancements.AdvancementType.CHALLENGE","net.minecraft.advancements.AdvancementRewards$Builder.experience","net.minecraft.advancements.Advancement$Builder.rewards","net.minecraft.advancements.criterion.MinMaxBounds$Doubles.atLeast","net.minecraft.advancements.criterion.DistancePredicate.vertical","net.minecraft.advancements.criterion.LevitationTrigger$TriggerInstance.levitated","net.minecraft.world.item.Items.ELYTRA","net.minecraft.world.level.block.Blocks.DRAGON_EGG"],"usages":["net.minecraft.data.advancements.packs.VanillaAdvancementProvider"]}
