{"name":"ErrorCollector$LongestOnly$MutableErrorEntry","package":"net.minecraft.util.parsing.packrat","fqn":"net.minecraft.util.parsing.packrat.ErrorCollector$LongestOnly$MutableErrorEntry","type":"class","members":["private net.minecraft.util.parsing.packrat.SuggestionSupplier<S> suggestions;","private java.lang.Object reason;","private net.minecraft.util.parsing.packrat.ErrorCollector$LongestOnly$MutableErrorEntry();"],"references":["net.minecraft.util.parsing.packrat.SuggestionSupplier.empty"],"usages":["net.minecraft.util.parsing.packrat.ErrorCollector$LongestOnly"]}
