{"name":"TryFindWaterGoal","package":"net.minecraft.world.entity.ai.goal","fqn":"net.minecraft.world.entity.ai.goal.TryFindWaterGoal","type":"class","members":["private final net.minecraft.world.entity.PathfinderMob mob;","public net.minecraft.world.entity.ai.goal.TryFindWaterGoal(net.minecraft.world.entity.PathfinderMob);","public boolean canUse();","public void start();"],"references":["net.minecraft.world.entity.ai.goal.Goal","net.minecraft.world.entity.PathfinderMob.onGround","net.minecraft.world.entity.PathfinderMob.level","net.minecraft.world.entity.PathfinderMob.blockPosition","net.minecraft.world.level.Level.getFluidState","net.minecraft.tags.FluidTags.WATER","net.minecraft.world.level.material.FluidState.is","net.minecraft.world.entity.PathfinderMob.getX","net.minecraft.util.Mth.floor","net.minecraft.world.entity.PathfinderMob.getY","net.minecraft.world.entity.PathfinderMob.getZ","net.minecraft.world.entity.PathfinderMob.getBlockY","net.minecraft.core.BlockPos.betweenClosed","net.minecraft.core.BlockPos","net.minecraft.world.entity.PathfinderMob.getMoveControl","net.minecraft.core.BlockPos.getX","net.minecraft.core.BlockPos.getY","net.minecraft.core.BlockPos.getZ","net.minecraft.world.entity.ai.control.MoveControl.setWantedPosition"],"usages":["net.minecraft.world.entity.animal.dolphin.Dolphin"]}
