{"name":"ScreenNarrationCollector$NarrationEntry","package":"net.minecraft.client.gui.narration","fqn":"net.minecraft.client.gui.narration.ScreenNarrationCollector$NarrationEntry","type":"class","members":["private net.minecraft.client.gui.narration.NarrationThunk<?> contents;","private int generation;","private boolean alreadyNarrated;","private net.minecraft.client.gui.narration.ScreenNarrationCollector$NarrationEntry();","public net.minecraft.client.gui.narration.ScreenNarrationCollector$NarrationEntry update(int, net.minecraft.client.gui.narration.NarrationThunk<?>);"],"references":["net.minecraft.client.gui.narration.NarrationThunk.EMPTY","net.minecraft.client.gui.narration.NarrationThunk.equals"],"usages":["net.minecraft.client.gui.narration.ScreenNarrationCollector$Output"]}
