{"name":"Style$Serializer","package":"net.minecraft.network.chat","fqn":"net.minecraft.network.chat.Style$Serializer","type":"class","members":["public static final com.mojang.serialization.MapCodec<net.minecraft.network.chat.Style> MAP_CODEC;","public static final com.mojang.serialization.Codec<net.minecraft.network.chat.Style> CODEC;","public static final net.minecraft.network.codec.StreamCodec<net.minecraft.network.RegistryFriendlyByteBuf, net.minecraft.network.chat.Style> TRUSTED_STREAM_CODEC;","public net.minecraft.network.chat.Style$Serializer();","private static com.mojang.datafixers.kinds.App lambda$static$11(com.mojang.serialization.codecs.RecordCodecBuilder$Instance);","private static java.util.Optional lambda$static$10(net.minecraft.network.chat.Style);","private static java.util.Optional lambda$static$9(net.minecraft.network.chat.Style);","private static java.util.Optional lambda$static$8(net.minecraft.network.chat.Style);","private static java.util.Optional lambda$static$7(net.minecraft.network.chat.Style);","private static java.util.Optional lambda$static$6(net.minecraft.network.chat.Style);","private static java.util.Optional lambda$static$5(net.minecraft.network.chat.Style);","private static java.util.Optional lambda$static$4(net.minecraft.network.chat.Style);","private static java.util.Optional lambda$static$3(net.minecraft.network.chat.Style);","private static java.util.Optional lambda$static$2(net.minecraft.network.chat.Style);","private static java.util.Optional lambda$static$1(net.minecraft.network.chat.Style);","private static java.util.Optional lambda$static$0(net.minecraft.network.chat.Style);","static {};"],"references":["net.minecraft.network.chat.TextColor.CODEC","com.mojang.serialization.Codec.optionalFieldOf","com.mojang.serialization.MapCodec.forGetter","net.minecraft.util.ExtraCodecs.ARGB_COLOR_CODEC","com.mojang.serialization.Codec.BOOL","com.mojang.serialization.codecs.PrimitiveCodec.optionalFieldOf","net.minecraft.network.chat.ClickEvent.CODEC","net.minecraft.network.chat.HoverEvent.CODEC","com.mojang.serialization.Codec.STRING","net.minecraft.network.chat.FontDescription.CODEC","com.mojang.serialization.codecs.RecordCodecBuilder$Instance.group","com.mojang.datafixers.Products$P11.apply","net.minecraft.network.chat.Style.font","net.minecraft.network.chat.Style.insertion","net.minecraft.network.chat.Style.hoverEvent","net.minecraft.network.chat.Style.clickEvent","net.minecraft.network.chat.Style.obfuscated","net.minecraft.network.chat.Style.strikethrough","net.minecraft.network.chat.Style.underlined","net.minecraft.network.chat.Style.italic","net.minecraft.network.chat.Style.bold","net.minecraft.network.chat.Style.shadowColor","net.minecraft.network.chat.Style.color","com.mojang.serialization.codecs.RecordCodecBuilder.mapCodec","com.mojang.serialization.MapCodec.codec","net.minecraft.network.codec.ByteBufCodecs.fromCodecWithRegistriesTrusted"],"usages":[]}
