{"name":"ComponentPredicateParser$TagLookupRule","package":"net.minecraft.commands.arguments.item","fqn":"net.minecraft.commands.arguments.item.ComponentPredicateParser$TagLookupRule","type":"class","members":["private net.minecraft.commands.arguments.item.ComponentPredicateParser$TagLookupRule(net.minecraft.util.parsing.packrat.NamedRule<com.mojang.brigadier.StringReader, net.minecraft.resources.Identifier>, net.minecraft.commands.arguments.item.ComponentPredicateParser$Context<T, C, P>);","protected T validateElement(com.mojang.brigadier.ImmutableStringReader, net.minecraft.resources.Identifier) throws java.lang.Exception;","public java.util.stream.Stream<net.minecraft.resources.Identifier> possibleResources();"],"references":["net.minecraft.util.parsing.packrat.commands.ResourceLookupRule","net.minecraft.commands.arguments.item.ComponentPredicateParser$Context","net.minecraft.commands.arguments.item.ComponentPredicateParser$Context.forTagType","net.minecraft.commands.arguments.item.ComponentPredicateParser$Context.listTagTypes"],"usages":["net.minecraft.commands.arguments.item.ComponentPredicateParser"]}
