{"name":"Turtle$TurtleMoveControl","package":"net.minecraft.world.entity.animal.turtle","fqn":"net.minecraft.world.entity.animal.turtle.Turtle$TurtleMoveControl","type":"class","members":["private final net.minecraft.world.entity.animal.turtle.Turtle turtle;","net.minecraft.world.entity.animal.turtle.Turtle$TurtleMoveControl(net.minecraft.world.entity.animal.turtle.Turtle);","private void updateSpeed();","public void tick();"],"references":["net.minecraft.world.entity.ai.control.MoveControl","net.minecraft.world.entity.animal.turtle.Turtle.isInWater","net.minecraft.world.entity.animal.turtle.Turtle.getDeltaMovement","net.minecraft.world.phys.Vec3.add","net.minecraft.world.entity.animal.turtle.Turtle.setDeltaMovement","net.minecraft.world.entity.animal.turtle.Turtle.homePos","net.minecraft.world.entity.animal.turtle.Turtle.position","net.minecraft.core.BlockPos.closerToCenterThan","net.minecraft.world.entity.animal.turtle.Turtle.getSpeed","net.minecraft.world.entity.animal.turtle.Turtle.setSpeed","net.minecraft.world.entity.animal.turtle.Turtle.isBaby","net.minecraft.world.entity.animal.turtle.Turtle.onGround","net.minecraft.world.entity.ai.control.MoveControl$Operation.MOVE_TO","net.minecraft.world.entity.animal.turtle.Turtle.getNavigation","net.minecraft.world.entity.ai.navigation.PathNavigation.isDone","net.minecraft.world.entity.animal.turtle.Turtle.getX","net.minecraft.world.entity.animal.turtle.Turtle.getY","net.minecraft.world.entity.animal.turtle.Turtle.getZ","net.minecraft.world.entity.Mob.setSpeed","net.minecraft.util.Mth.atan2","net.minecraft.world.entity.animal.turtle.Turtle.getYRot","net.minecraft.world.entity.animal.turtle.Turtle.setYRot","net.minecraft.world.entity.animal.turtle.Turtle.yBodyRot","net.minecraft.world.entity.ai.attributes.Attributes.MOVEMENT_SPEED","net.minecraft.world.entity.animal.turtle.Turtle.getAttributeValue","net.minecraft.util.Mth.lerp"],"usages":["net.minecraft.world.entity.animal.turtle.Turtle"]}
